{
  "name": "Bobby Phelps",
  "age": 53,
  "address": {
    "street": "Aptic Place",
    "city": "Pecociri",
    "state": "HI",
    "zip": "07552"
  },
  "contact": {
    "phone": "(418) 729-4060",
    "servicePhone": "800645725"
  },
  "birthday": "1986-09-11T04:03:55.469Z",
  "ip": "185.184.215.135",
  "foo": "bar",
  "profile": {
    "about": "Wudcajlul zudi asfib pehob at tapkawi pawib hutiz gilpinus wekobipih dujagzo objez ozamaofu wimu vaidu wug dop. Miz ki rismuk iju awoke votol imehovi sefilu sur owci er kifjefog fik gup goak. Nudowo benakow vorto mesjido was ge vo jojatjat tovaznan conodak su cuzeb lop. Meme tiwid itu kawehtu nas giweh nonuzo ofeozimu te piliz jorafho migfun wuj hocbe ahinimed bajvalbah. Udolun odnuve cato pu obucume wojla buflu liv poltifofi pap refzuc fuuvuwag ruwul bejug oti pu eri. Sarizwu emo ce fufof cizur ji rega sejco kejjor potetfu bojmo giuvmi.",
    "bio": "Gihwe junal haije sa mevug zab ava mecov lazonogub itouho hopos mebo sigehu pojpus ha. Tehepgan suko haham awe cunmaen ug poiliti imsam ewpog jik can nac. Kuole op lonpahe wecac oldebfig gi for fendol vo ehudut bolrobgoz hez horbil. Ad vapaba do nep vujesuwi dahorer cu gorpem zufif muwcoewa jipcifre cowo. Ulhaz niku zo ric socoume hangi wi nih gielefit voriw tubuz gifvug nirjacma fa."
  },
  "apiKey": "8492815a809cf1bf0b7046d8ac530299d310aefbc40949c3740fc52bd0c1c7f5",
  "currency": {
    "code": "FKP",
    "name": "Falkland Islands (Malvinas) Pound"
  }
}